moonlightplt/Animator.py
moonlightplt/__init__.py
moonlightplt/utils.py
moonlightplt/waves/Cosine.py
moonlightplt/waves/Sawtooth.py
moonlightplt/waves/Sine.py
moonlightplt/waves/Square.py
moonlightplt/waves/Wave.py
moonlightplt/waves/__init__.py
moonlightplt-0.2.2.dist-info/METADATA
moonlightplt-0.2.2.dist-info/WHEEL
moonlightplt-0.2.2.dist-info/top_level.txt
moonlightplt-0.2.2.dist-info/RECORD
