Metadata-Version: 2.1
Name: moonlightplt
Version: 0.2.2
Summary: Matplotlib wave plotting and animation made easy
Home-page: https://github.com/CharlesAverill/moonlightplt/
Author: Charles Averill
Author-email: charlesaverill20@gmail.com
License: UNKNOWN
Platform: UNKNOWN
Classifier: Programming Language :: Python :: 3
Classifier: License :: OSI Approved :: MIT License
Classifier: Operating System :: OS Independent
Classifier: Framework :: Matplotlib
Requires-Dist: matplotlib
Requires-Dist: numpy
Requires-Dist: scipy
